pyctrsa/__init__.py
pyctrsa/ctrdm/__init__.py
pyctrsa/ctrdm/multi_cal.py
pyctrsa/ctrdm/single_cal.py
pyctrsa/ctsimilarity/__init__.py
pyctrsa/ctsimilarity/fitctrdm.py
pyctrsa/ctsimilarity/normaldatabased.py
pyctrsa/ctsimilarity/normalrdmbased.py
pyctrsa/plotting/__init__.py
pyctrsa/plotting/ctrdm.py
pyctrsa/plotting/ctsimilarities.py
pyctrsa/plotting/tbytsimilarities.py
pyctrsa/similarity/__init__.py
pyctrsa/similarity/cosinesimilarity.py
pyctrsa/similarity/euclideandistance.py
pyctrsa/similarity/kendallrp.py
pyctrsa/similarity/pearsonrp.py
pyctrsa/similarity/spearmanrp.py
pyctrsa/util/__init__.py
pyctrsa/util/download_data.py
pyctrsa/util/makedir.py
pyctrsa/util/preprocess_data.py
pyctrsa/util/progressbar.py
pyctrsa/util/unzip_data.py
pyctrsa-0.1.0.dist-info/LICENSE
pyctrsa-0.1.0.dist-info/METADATA
pyctrsa-0.1.0.dist-info/WHEEL
pyctrsa-0.1.0.dist-info/top_level.txt
pyctrsa-0.1.0.dist-info/RECORD
