Metadata-Version: 2.1
Name: pyctrsa
Version: 0.1.0
Summary: A Python Toolbox for Cross-Temporal Representational Similarity Analysis-based Decoding on E/MEG Data
Home-page: https://github.com/ZitongLu1996/PyCTRSA
Author: Zitong Lu
Author-email: zitonglu1996@gmail.com
Maintainer: Zitong Lu
Maintainer-email: zitonglu1996@gmail.com
License: MIT License
Platform: all
Classifier: Development Status :: 4 - Beta
Classifier: Operating System :: OS Independent
Classifier: Intended Audience :: Developers
Classifier: License :: OSI Approved :: BSD License
Classifier: Programming Language :: Python
Classifier: Programming Language :: Python :: Implementation
Classifier: Programming Language :: Python :: 2
Classifier: Programming Language :: Python :: 2.7
Classifier: Programming Language :: Python :: 3
Classifier: Programming Language :: Python :: 3.4
Classifier: Programming Language :: Python :: 3.5
Classifier: Programming Language :: Python :: 3.6
Classifier: Topic :: Software Development :: Libraries
Requires-Dist: numpy
Requires-Dist: scipy (>=1.4)
Requires-Dist: matplotlib
Requires-Dist: neurora
